[{
	"MemberID": "12345678",
	"FirstName": "John",
	"LastName": "Doe",
	"Gender": "Male",
	"EmailAddress": "johndoe@iu.edu",
	"PhoneNumber": "123-123-1234",
	"Weight": "180",
	"Age": "45",
	"FitnessGoal": "Weight Loss",
	"CaloriesBurned": "150",
	"Miles": "10",
	"WeightGoal": "590",
	"Steps": "10,000",
	"FloorsClimbed": "80"
}, {
	"MemberID": "28394038",
	"FirstName": "Jane",
	"LastName": "Dan",
	"Gender": "Female",
	"EmailAddress": "jandan@iu.edu",
	"PhoneNumber": "738-394-1923",
	"Weight": "150",
	"Age": "32",	
	"FitnessGoal": "Weight Loss",
	"CaloriesBurned": "430",
	"Miles": 105,
	"WeightGoal": "135",
	"Steps": "10,320",
	"FloorsClimbed": "233"
},{
	"MemberID": "34950495",
	"FirstName": "Ji",
	"LastName": "Lee",
	"Gender": "Male",
	"EmailAddress": "lee943@iu.edu",
	"PhoneNumber": "329-439-4930",
	"Weight": "150",
	"FitnessGoal": "Weight Loss",
	"CaloriesBurned": "4,430",
	"Miles": "503",
	"WeightGoal": "140",
	"Steps": "9,239",
	"FloorsClimbed": "520"
},{
	"MemberID": "49302748",
	"FirstName": "Matt",
	"LastName": "Boothby",
	"Gender": "Male",
	"EmailAddress": "boothby@iu.edu",
	"PhoneNumber": "438-238-4381",
	"Weight": "135",
	"FitnessGoal": "Athletic Performance",
	"CaloriesBurned": "493",
	"Miles": "854",
	"WeightGoal": "140",
	"Steps": "15,540",
	"FloorsClimbed": "604"
},{
	"MemberID": "39204739",
	"FirstName": "Kim",
	"LastName": "Smith",
	"Gender": "Female",
	"EmailAddress": "ksmith@iu.edu",
	"PhoneNumber": "430-234-0192",
	"Weight": "128",
	"FitnessGoal": "Overall Health",
	"CaloriesBurned": "540",
	"Miles": "650",
	"WeightGoal": "125",
	"Steps": "9,540",
	"FloorClimbed": "954"
},{
	"MemberID": "9285930",
	"FirstName": "Patty",
	"LastName": "Smith",
	"Gender": "Female",
	"EmailAddress": "ktanner@iu.edu",
	"PhoneNumber": "420-234-5943",
	"Weight": "119",
	"FitnessGoal": "Weight Management",
	"CaloriesBurned": "845",
	"Miles": "852",
	"WeightGoal": "115",
	"Steps": "6,395",
	"FloorClimbed": "1,240"
}]